auramcp/__init__.py
auramcp/cli.py
auramcp/auth/__init__.py
auramcp/auth/handlers.py
auramcp/auth/registry.py
auramcp/auth/configs/_template.yaml
auramcp/auth/configs/airtable.yaml
auramcp/auth/configs/github.yaml
auramcp/auth/configs/notion.yaml
auramcp/auth/configs/slack.yaml
auramcp/auth/configs/stripe.yaml
auramcp/generator/__init__.py
auramcp/generator/codegen.py
auramcp/generator/converter.py
auramcp/generator/parser.py
auramcp/generator/reviewer.py
auramcp/specs/__init__.py
auramcp/specs/fetcher.py
auramcp/specs/registry.py
auramcp/testing/__init__.py
auramcp-0.1.3.dist-info/METADATA
auramcp-0.1.3.dist-info/WHEEL
auramcp-0.1.3.dist-info/entry_points.txt
auramcp-0.1.3.dist-info/RECORD
