Metadata-Version: 2.4
Name: auramcp
Version: 0.1.3
Summary: Universal MCP Server Generator - Create MCP servers from any OpenAPI spec
Project-URL: Homepage, https://github.com/simpaira/auramcp
Project-URL: Documentation, https://github.com/simpaira/auramcp#readme
Project-URL: Repository, https://github.com/simpaira/auramcp
Project-URL: Issues, https://github.com/simpaira/auramcp/issues
Project-URL: Changelog, https://github.com/simpaira/auramcp/releases
Author-email: Simpaira <info@simpaira.com>
Maintainer-email: Simpaira <info@simpaira.com>
License-Expression: MIT
Keywords: anthropic,api,claude,generator,llm,mcp,model-context-protocol,openapi
Classifier: Development Status :: 4 - Beta
Classifier: Intended Audience :: Developers
Classifier: License :: OSI Approved :: MIT License
Classifier: Programming Language :: Python :: 3
Classifier: Programming Language :: Python :: 3.10
Classifier: Programming Language :: Python :: 3.11
Classifier: Programming Language :: Python :: 3.12
Classifier: Programming Language :: Python :: 3.13
Classifier: Topic :: Software Development :: Code Generators
Classifier: Topic :: Software Development :: Libraries :: Python Modules
Requires-Python: >=3.10
Requires-Dist: click>=8.0.0
Requires-Dist: httpx>=0.25.0
Requires-Dist: jinja2>=3.0.0
Requires-Dist: jsonschema>=4.0.0
Requires-Dist: mcp>=1.0.0
Requires-Dist: pydantic>=2.0.0
Requires-Dist: pyyaml>=6.0
Requires-Dist: rich>=13.0.0
Provides-Extra: dev
Requires-Dist: black>=23.0.0; extra == 'dev'
Requires-Dist: mypy>=1.0.0; extra == 'dev'
Requires-Dist: pytest-asyncio>=0.21.0; extra == 'dev'
Requires-Dist: pytest-cov>=4.0.0; extra == 'dev'
Requires-Dist: pytest>=7.0.0; extra == 'dev'
Requires-Dist: ruff>=0.1.0; extra == 'dev'
Provides-Extra: llm
Requires-Dist: anthropic>=0.18.0; extra == 'llm'
